substratum/__init__.py
substratum-0.1.0a1.dist-info/LICENSE
substratum-0.1.0a1.dist-info/METADATA
substratum-0.1.0a1.dist-info/WHEEL
substratum-0.1.0a1.dist-info/top_level.txt
substratum-0.1.0a1.dist-info/RECORD
